herodotus/__init__.py
herodotus/handlers/__init__.py
herodotus/handlers/enhanced_handler.py
herodotus/handlers/file_handlers.py
herodotus/handlers/stream_handlers.py
herodotus/logger/__init__.py
herodotus/logger/logger.py
herodotus/utils/__init__.py
herodotus/utils/colorizer.py
herodotus_logger-1.3.2.dist-info/licenses/LICENSE.txt
herodotus_logger-1.3.2.dist-info/METADATA
herodotus_logger-1.3.2.dist-info/WHEEL
herodotus_logger-1.3.2.dist-info/top_level.txt
herodotus_logger-1.3.2.dist-info/RECORD
