Metadata-Version: 2.4
Name: herodotus_logger
Version: 1.3.2
Summary: An enhanced python logger
Author-email: Emad Helmi <s.emad.helmi@gmail.com>
License: MIT
Project-URL: Homepage, https://github.com/EmadHelmi/herodotus
Project-URL: IssueTracker, https://github.com/EmadHelmi/herodotus/issues
Project-URL: Repository, https://github.com/EmadHelmi/herodotus
Classifier: Programming Language :: Python :: 3
Classifier: License :: OSI Approved :: MIT License
Classifier: Operating System :: OS Independent
Requires-Python: >=3.11
License-File: LICENSE.txt
Requires-Dist: colored>=2.2.3
Requires-Dist: concurrent-log-handler>=0.9.28
Dynamic: license-file
